_version.py
hexed/__init__.py
hexed/__main__.py
hexed/cli.py
hexed-0.0.1.dev13.dist-info/AUTHORS.rst
hexed-0.0.1.dev13.dist-info/LICENSE
hexed-0.0.1.dev13.dist-info/METADATA
hexed-0.0.1.dev13.dist-info/WHEEL
hexed-0.0.1.dev13.dist-info/entry_points.txt
hexed-0.0.1.dev13.dist-info/top_level.txt
hexed-0.0.1.dev13.dist-info/RECORD
